{
  "_class": "rectangle",
  "booleanOperation": -1,
  "clippingMaskMode": 0,
  "do_objectID": "D1FF2220-4CE6-4012-BE92-88BB305B72B7",
  "edited": false,
  "exportOptions": {
    "_class": "exportOptions",
    "do_objectID": "807D7A9B-5D2C-4CE2-B81C-1579110AA03A",
    "exportFormats": [
    ],
    "includedLayerIds": [
    ],
    "layerOptions": 0,
    "shouldTrim": false
  },
  "fixedRadius": 8,
  "frame": {
    "_class": "rect",
    "constrainProportions": false,
    "height": 40,
    "width": 158,
    "x": 108,
    "y": 455
  },
  "hasClippingMask": false,
  "hasConvertedToNewRoundCorners": true,
  "isClosed": true,
  "isFixedToViewport": false,
  "isFlippedHorizontal": false,
  "isFlippedVertical": false,
  "isLocked": false,
  "isVisible": true,
  "layerListExpandedType": 1,
  "name": "Rectangle",
  "nameIsFixed": false,
  "pointRadiusBehaviour": 1,
  "points": [
    {
      "_class": "curvePoint",
      "cornerRadius": 8,
      "curveFrom": "{0, 0}",
      "curveMode": 1,
      "curveTo": "{0, 0}",
      "hasCurveFrom": false,
      "hasCurveTo": false,
      "point": "{0, 0}"
    },
    {
      "_class": "curvePoint",
      "cornerRadius": 8,
      "curveFrom": "{1, 0}",
      "curveMode": 1,
      "curveTo": "{1, 0}",
      "hasCurveFrom": false,
      "hasCurveTo": false,
      "point": "{1, 0}"
    },
    {
      "_class": "curvePoint",
      "cornerRadius": 8,
      "curveFrom": "{1, 1}",
      "curveMode": 1,
      "curveTo": "{1, 1}",
      "hasCurveFrom": false,
      "hasCurveTo": false,
      "point": "{1, 1}"
    },
    {
      "_class": "curvePoint",
      "cornerRadius": 8,
      "curveFrom": "{0, 1}",
      "curveMode": 1,
      "curveTo": "{0, 1}",
      "hasCurveFrom": false,
      "hasCurveTo": false,
      "point": "{0, 1}"
    }
  ],
  "resizingConstraint": 63,
  "resizingType": 0,
  "rotation": 0,
  "shouldBreakMaskChain": false,
  "style": {
    "_class": "style",
    "borders": [
      {
        "_class": "border",
        "color": {
          "_class": "color",
          "alpha": 1,
          "blue": 0.3796647787094116,
          "green": 0.4135999381542206,
          "red": 0.4816333055496216
        },
        "fillType": 0,
        "isEnabled": true,
        "position": 1,
        "thickness": 1.05
      }
    ],
    "do_objectID": "E38449B0-AEB1-4C98-9D5C-BD0C6D8C7222",
    "endMarkerType": 0,
    "fills": [
      {
        "_class": "fill",
        "color": {
          "_class": "color",
          "alpha": 1,
          "blue": 0.7666714787483215,
          "green": 0.8887336254119873,
          "red": 0.9657279849052429
        },
        "fillType": 0,
        "isEnabled": true,
        "noiseIndex": 0,
        "noiseIntensity": 0,
        "patternFillType": 1,
        "patternTileScale": 1
      }
    ],
    "miterLimit": 10,
    "startMarkerType": 0,
    "windingRule": 1
  },
  "userInfo": {
  }
}